llm_duckduckgo_chat.py
llm_duckduckgo_chat-0.1.6.dist-info/licenses/LICENSE
llm_duckduckgo_chat-0.1.6.dist-info/METADATA
llm_duckduckgo_chat-0.1.6.dist-info/WHEEL
llm_duckduckgo_chat-0.1.6.dist-info/entry_points.txt
llm_duckduckgo_chat-0.1.6.dist-info/top_level.txt
llm_duckduckgo_chat-0.1.6.dist-info/RECORD
