Metadata-Version: 2.4
Name: llm-duckduckgo-chat
Version: 0.1.6
Summary: LLM plugin for Duckduckgo AI Chat service
Author: Sukhbinder Singh
License: Apache-2.0
Project-URL: Homepage, https://github.com/sukhbinder/llm-duckduckgo-chat
Project-URL: Changelog, https://github.com/sukhbinder/llm-duckduckgo-chat/releases
Project-URL: Issues, https://github.com/sukhbinder/llm-duckduckgo-chat/issues
Project-URL: CI, https://github.com/sukhbinder/llm-duckduckgo-chat/actions
Classifier: License :: OSI Approved :: Apache Software License
Requires-Python: >=3.9
License-File: LICENSE
Requires-Dist: llm
Requires-Dist: requests
Provides-Extra: test
Requires-Dist: pytest; extra == "test"
Dynamic: license-file
